python_print_color/__init__.py
python_print_color-0.0.2.dist-info/LICENSE
python_print_color-0.0.2.dist-info/METADATA
python_print_color-0.0.2.dist-info/WHEEL
python_print_color-0.0.2.dist-info/top_level.txt
python_print_color-0.0.2.dist-info/RECORD
