Metadata-Version: 2.1
Name: python-print-color
Version: 0.0.2
Summary: These Python functions allow you to print text with various colors and styles in your terminal with ANSI escape sequences
Home-page: https://github.com/Nicorebo-18/Python-Print-With-Color
Author: Nicorebo-18
Author-email: nicorebo18@gmail.com
Project-URL: Bug Tracker, https://github.com/Nicorebo-18/Python-Print-With-Color/issues
Classifier: Programming Language :: Python :: 3
Classifier: License :: OSI Approved :: MIT License
Classifier: Operating System :: OS Independent
Requires-Python: >=3.6
License-File: LICENSE
